MANIFEST.in
README.rst
setup.py
BasiliskJS.egg-info/PKG-INFO
BasiliskJS.egg-info/SOURCES.txt
BasiliskJS.egg-info/dependency_links.txt
BasiliskJS.egg-info/not-zip-safe
BasiliskJS.egg-info/top_level.txt
basilisk/__init__.py
basilisk/__init__.pyc
basilisk/basilisk.py
basilisk/basilisk.pyc