Metadata-Version: 1.1
Name: BasiliskJS
Version: 0.8
Summary: Web browser emulator, based on PhantomJS
Home-page: https://github.com/lich666dead/BasiliskJS
Author: lich666dead
Author-email: lich666black@gmail.com
License: GNU General Public License v3 (GPLv3)
Download-URL: https://github.com/lich666dead/BasiliskJS/archive/master.zip
Platform: any
Classifier: Environment :: Web Environment
Classifier: License :: OSI Approved :: GNU General Public License v3 (GPLv3)
Classifier: Natural Language :: Russian
Classifier: Operating System :: OS Independent
Classifier: Programming Language :: Python
Classifier: Programming Language :: Python :: 2.6
Classifier: Programming Language :: Python :: 2.7
Classifier: Programming Language :: Python :: 3
Classifier: Programming Language :: Python :: 3.4
Classifier: Programming Language :: Python :: 3.5
Classifier: Programming Language :: Python :: 3.6
Classifier: Topic :: Internet :: WWW/HTTP :: Dynamic Content
Classifier: Topic :: Software Development :: Libraries :: Python Modules
